odoo/addons/stock_batch_picking/README.rst
odoo/addons/stock_batch_picking/__init__.py
odoo/addons/stock_batch_picking/__manifest__.py
odoo/addons/stock_batch_picking/data/batch_picking_actions_server.xml
odoo/addons/stock_batch_picking/data/stock_batch_picking_sequence.xml
odoo/addons/stock_batch_picking/i18n/de.po
odoo/addons/stock_batch_picking/i18n/es.po
odoo/addons/stock_batch_picking/i18n/fr.po
odoo/addons/stock_batch_picking/i18n/it.po
odoo/addons/stock_batch_picking/i18n/pt_BR.po
odoo/addons/stock_batch_picking/i18n/sl.po
odoo/addons/stock_batch_picking/i18n/stock_batch_picking.pot
odoo/addons/stock_batch_picking/models/__init__.py
odoo/addons/stock_batch_picking/models/product_product.py
odoo/addons/stock_batch_picking/models/stock_batch_picking.py
odoo/addons/stock_batch_picking/models/stock_picking.py
odoo/addons/stock_batch_picking/models/stock_warehouse.py
odoo/addons/stock_batch_picking/readme/CONTRIBUTORS.rst
odoo/addons/stock_batch_picking/readme/DESCRIPTION.rst
odoo/addons/stock_batch_picking/report/__init__.py
odoo/addons/stock_batch_picking/report/batch_report.py
odoo/addons/stock_batch_picking/security/ir.model.access.csv
odoo/addons/stock_batch_picking/static/batch_form.png
odoo/addons/stock_batch_picking/static/batch_form_operation.png
odoo/addons/stock_batch_picking/static/batch_wizard.png
odoo/addons/stock_batch_picking/static/stock_picking_list.png
odoo/addons/stock_batch_picking/static/description/icon.png
odoo/addons/stock_batch_picking/static/description/index.html
odoo/addons/stock_batch_picking/tests/__init__.py
odoo/addons/stock_batch_picking/tests/test_batch.py
odoo/addons/stock_batch_picking/views/product_product.xml
odoo/addons/stock_batch_picking/views/report_batch_picking.xml
odoo/addons/stock_batch_picking/views/stock_batch_picking.xml
odoo/addons/stock_batch_picking/views/stock_picking.xml
odoo/addons/stock_batch_picking/views/stock_warehouse.xml
odoo/addons/stock_batch_picking/wizard/__init__.py
odoo11_addon_stock_batch_picking-11.0.1.4.0.dist-info/METADATA
odoo11_addon_stock_batch_picking-11.0.1.4.0.dist-info/WHEEL
odoo11_addon_stock_batch_picking-11.0.1.4.0.dist-info/top_level.txt
odoo11_addon_stock_batch_picking-11.0.1.4.0.dist-info/RECORD
